hratio/__init__.py
adaptivelcbin-0.1.13.dist-info/LICENSE
adaptivelcbin-0.1.13.dist-info/METADATA
adaptivelcbin-0.1.13.dist-info/WHEEL
adaptivelcbin-0.1.13.dist-info/entry_points.txt
adaptivelcbin-0.1.13.dist-info/top_level.txt
adaptivelcbin-0.1.13.dist-info/RECORD
