Metadata-Version: 2.1
Name: adaptivelcbin
Version: 0.1.13
Summary: adaptivelcbin
Home-page: https://gitlab.astro.unige.ch/ferrigno/adaptivelcbin
Author: C.F.
Author-email: carlo.ferrigno@unige.ch
License: MIT
Classifier: Development Status :: 4 - Beta
Classifier: Environment :: Console
Classifier: Intended Audience :: Science/Research
Classifier: License :: OSI Approved :: MIT License
Classifier: Operating System :: POSIX
Classifier: Programming Language :: Python :: 3.4
Classifier: Programming Language :: Python :: 3.5
Classifier: Programming Language :: Python :: 3.6
Classifier: Programming Language :: Python :: 3.7
Classifier: Programming Language :: Python :: 3.8
Classifier: Topic :: Internet
Classifier: Topic :: Scientific/Engineering :: Astronomy
License-File: LICENSE
Requires-Dist: astropy
Requires-Dist: numpy
Requires-Dist: click
